Good question 👍 Let’s break it super simply with **code + table**.

---

### 1. `Iterable`

* **Interface** in Java (`java.lang.Iterable`).
* Has method `iterator()` → gives an `Iterator`.
* Any class that implements `Iterable` can be used in **enhanced for-each loop**.

```java
List<String> fruits = List.of("Apple", "Banana", "Mango");

// Using Iterable explicitly
Iterator<String> it = fruits.iterator();
while(it.hasNext()) {
    System.out.println(it.next());
}
```

---

### 2. **For-each loop**

* **Language construct** (syntactic sugar).
* Internally uses the `Iterator` from `Iterable`.
* Easier to read/write.

```java
for(String fruit : fruits) {
    System.out.println(fruit);
}
```

---

### 🔑 Quick Difference (Interview-Ready)

| Feature                  | Iterable                                         | For-each Loop                            |
| ------------------------ | ------------------------------------------------ | ---------------------------------------- |
| **Type**                 | Interface (`java.lang.Iterable`)                 | Language construct (syntax sugar)        |
| **Method**               | `iterator()` returns `Iterator`                  | Uses `Iterable.iterator()` inside        |
| **Usage**                | Explicit iteration with `hasNext()` + `next()`   | Simple clean loop (`for(x : y)`)         |
| **Control**              | More control (remove elements, custom iteration) | Less control (no remove while iterating) |
| **Who depends on whom?** | For-each loop **needs Iterable**                 | Iterable **doesn’t need** for-each       |

---

👉 In short:

* **Iterable = capability** (provides iterator).
* **For-each = shortcut** (uses that iterator automatically).

---

Do you want me to also show **what compiler generates** when you use for-each (so you see how it turns into `Iterator` code)?


---
---

# Yes


## 🔁 for-each → What Compiler Generates (Desugared Code)

### 1️⃣ For Collections (`Iterable`)

### Your Code

```java
List<String> list = List.of("A", "B", "C");

for (String s : list) {
    System.out.println(s);
}
```

### 👇 Compiler Generates (Approx Equivalent)

```java
List<String> list = List.of("A", "B", "C");

for (Iterator<String> it = list.iterator(); it.hasNext();) {
    String s = it.next();
    System.out.println(s);
}
```

✔ `list.iterator()`
✔ `it.hasNext()`
✔ `it.next()`

---

## 🔍 Actual Bytecode View

Compile:

```bash
javac Main.java
```

Disassemble:

```bash
javap -c Main
```

You’ll see something like:

```java
0: aload_1
1: invokeinterface #2,  1  // List.iterator()
6: astore_2
7: aload_2
8: invokeinterface #3,  1  // Iterator.hasNext()
13: ifeq          32
16: aload_2
17: invokeinterface #4,  1  // Iterator.next()
22: checkcast     #5       // String
25: astore_3
26: getstatic     #6       // System.out
29: aload_3
30: invokevirtual #7       // println
33: goto          7
```

---

# 2️⃣ For Arrays (Different Case)

### Your Code

```java
int[] arr = {1, 2, 3};

for (int i : arr) {
    System.out.println(i);
}
```

### 👇 Compiler Generates

```java
int[] arr = {1, 2, 3};

for (int index = 0; index < arr.length; index++) {
    int i = arr[index];
    System.out.println(i);
}
```

⚠ Arrays → No `Iterator`
⚠ Pure index-based loop

---

# 3️⃣ Generic Example (Important for Interview)

```java
for (Object obj : list)
```

Becomes:

```java
for (Iterator it = list.iterator(); it.hasNext();) {
    Object obj = it.next();
}
```

Raw type if generics erased.

---

# ⚠ Why You Can’t Modify Collection in for-each

Because internally:

```java
Iterator it = list.iterator();
```

And modifying collection directly causes:

```text
ConcurrentModificationException
```

Correct way:

```java
Iterator<String> it = list.iterator();
while (it.hasNext()) {
    if (it.next().equals("B")) {
        it.remove();
    }
}
```

---

# 🧠 Summary

| Type       | Compiled To      |
| ---------- | ---------------- |
| Collection | Iterator loop    |
| Array      | Index-based loop |

---

If you want next:

* How lambda `forEach()` compiles
* How Stream API compiles
* How try-with-resources compiles
* How switch expression compiles
* How autoboxing compiles

Tell me which internal transformation you want next 🚀
